{
  "variants": {
    "facing=east,honey_level=0": {
      "y": 90,
      "model": "jnether_expansion:block/soul_hive"
    },
    "facing=east,honey_level=1": {
      "y": 90,
      "model": "jnether_expansion:block/soul_hive_full"
    },
    "facing=north,honey_level=0": {
      "model": "jnether_expansion:block/soul_hive"
    },
    "facing=north,honey_level=1": {
      "model": "jnether_expansion:block/soul_hive_full"
    },
    "facing=south,honey_level=0": {
      "y": 180,
      "model": "jnether_expansion:block/soul_hive"
    },
    "facing=south,honey_level=1": {
      "y": 180,
      "model": "jnether_expansion:block/soul_hive_full"
    },
    "facing=west,honey_level=0": {
      "y": 270,
      "model": "jnether_expansion:block/soul_hive"
    },
    "facing=west,honey_level=1": {
      "y": 270,
      "model": "jnether_expansion:block/soul_hive_full"
    }
  }
}